evrm/__main__.py
evrm/bus.py
evrm/command.py
evrm/define.py
evrm/error.py
evrm/event.py
evrm/json.py
evrm/locks.py
evrm/object.py
evrm/parser.py
evrm/persist.py
evrm/reactor.py
evrm/repeater.py
evrm/run.py
evrm/thread.py
evrm/utils.py
evrm/modules/__init__.py
evrm/modules/cmd.py
evrm/modules/dbg.py
evrm/modules/err.py
evrm/modules/flt.py
evrm/modules/irc.py
evrm/modules/log.py
evrm/modules/mdl.py
evrm/modules/mod.py
evrm/modules/req.py
evrm/modules/rss.py
evrm/modules/shp.py
evrm/modules/sts.py
evrm/modules/tdo.py
evrm/modules/thr.py
evrm/modules/udp.py
evrm/modules/wsd.py
evrm-121.data/data/share/doc/evrm/README
evrm-121.data/data/share/doc/evrm/Wetboek-van-Strafrecht.txt
evrm-121.data/data/share/doc/evrm/about.rst
evrm-121.data/data/share/doc/evrm/conf.py
evrm-121.data/data/share/doc/evrm/index.rst
evrm-121.data/data/share/doc/evrm/manual.rst
evrm-121.data/data/share/doc/evrm/nederland2.jpg
evrm-121.data/data/share/doc/evrm/robots.txt
evrm-121.data/data/share/doc/evrm/skull.png
evrm-121.data/data/share/doc/evrm/source.rst
evrm-121.data/data/share/doc/evrm/_static/evrm.css
evrm-121.data/data/share/doc/evrm/_templates/base.rst
evrm-121.data/data/share/doc/evrm/_templates/class.rst
evrm-121.data/data/share/doc/evrm/_templates/module.rst
evrm-121.data/data/share/doc/evrm/txt/BIJWERKING
evrm-121.data/data/share/doc/evrm/txt/CONTACT
evrm-121.data/data/share/doc/evrm/txt/DOPAMINE
evrm-121.data/data/share/doc/evrm/txt/MADS
evrm-121.data/data/share/doc/evrm/txt/ONTWENNING
evrm-121.data/data/share/doc/evrm/txt/VERGIFTIGING
evrm-121.data/data/share/doc/evrm/txt/Wetboek-van-Strafrecht.txt
evrm-121.data/data/share/doc/evrm/txt/WvGGZ.rst
evrm-121.data/data/share/doc/evrm/txt/WvGGZ.txt
evrm-121.data/data/share/doc/evrm/txt/aangifte.rst
evrm-121.data/data/share/doc/evrm/txt/aantallen.rst
evrm-121.data/data/share/doc/evrm/txt/absoluut.rst
evrm-121.data/data/share/doc/evrm/txt/bedreiging.rst
evrm-121.data/data/share/doc/evrm/txt/beuker.rst
evrm-121.dist-info/METADATA
evrm-121.dist-info/WHEEL
evrm-121.dist-info/entry_points.txt
evrm-121.dist-info/top_level.txt
evrm-121.dist-info/zip-safe
evrm-121.dist-info/RECORD
