Metadata-Version: 2.1
Name: evrm
Version: 121
Summary: ANTIPSYCHOTICS - AKATHISIA - CATATONIA - SEDATION - SHOCKS - LETHAL CATATONIA
Author-email: Bart Thate <bthate@dds.nl>
License: Public Domain
Project-URL: home, https://pypi.org/project/evrm
Project-URL: bugs, https://github.com/bthate/evrm/issues
Project-URL: source, https://github.com/bthate/evrm
Classifier: Development Status :: 3 - Alpha
Classifier: License :: Public Domain
Classifier: Operating System :: Unix
Classifier: Programming Language :: Python
Classifier: Topic :: Utilities
Provides-Extra: dev
